feroxbuster_scan/__init__.py
feroxbuster_scan/feroxbuster_scan.py
feroxbuster_scan-1.1.1.dist-info/METADATA
feroxbuster_scan-1.1.1.dist-info/WHEEL
feroxbuster_scan-1.1.1.dist-info/entry_points.txt
feroxbuster_scan-1.1.1.dist-info/top_level.txt
feroxbuster_scan-1.1.1.dist-info/RECORD
