Metadata-Version: 2.1
Name: feroxbuster-scan
Version: 1.1.1
Summary: A tool to download, run, and generate reports for Feroxbuster scans
Author: Adithya A N
Author-email: your_email@example.com
Classifier: Programming Language :: Python :: 3
Classifier: License :: OSI Approved :: MIT License
Classifier: Operating System :: OS Independent
Requires-Python: >=3.6
Requires-Dist: requests
